setup.py
OpenGroupware.egg-info/PKG-INFO
OpenGroupware.egg-info/SOURCES.txt
OpenGroupware.egg-info/dependency_links.txt
OpenGroupware.egg-info/eager_resources.txt
OpenGroupware.egg-info/requires.txt
OpenGroupware.egg-info/top_level.txt
OpenGroupware.egg-info/zip-safe
coils/__init__.py
coils/core/__init__.py
coils/core/accessmanager.py
coils/core/authenticator.py
coils/core/broker.py
coils/core/bundlemanager.py
coils/core/command.py
coils/core/content_plugin.py
coils/core/context.py
coils/core/dbauthenticator.py
coils/core/entityaccessmanager.py
coils/core/exception.py
coils/core/ldapauthenticator.py
coils/core/ldaphelper.py
coils/core/linkmanager.py
coils/core/lockmanager.py
coils/core/master.py
coils/core/objinfomanager.py
coils/core/packet.py
coils/core/propertymanager.py
coils/core/service.py
coils/core/subservice.py
coils/core/threadedservice.py
coils/core/typemanager.py
coils/core/useragents.py
coils/core/utility.py
coils/core/icalendar/__init__.py
coils/core/icalendar/parse.py
coils/core/icalendar/parse_vevent.py
coils/core/icalendar/parse_vjournal.py
coils/core/icalendar/parse_vtodo.py
coils/core/icalendar/render.py
coils/core/icalendar/render_appointment.py
coils/core/icalendar/render_note.py
coils/core/icalendar/render_process.py
coils/core/icalendar/render_task.py
coils/core/logic/__init__.py
coils/core/logic/action.py
coils/core/logic/async.py
coils/core/logic/create.py
coils/core/logic/delete.py
coils/core/logic/get.py
coils/core/logic/keymap.py
coils/core/logic/macro.py
coils/core/logic/search.py
coils/core/logic/set.py
coils/core/logic/update.py
coils/core/omphalos/__init__.py
coils/core/omphalos/render.py
coils/core/omphalos/render_account.py
coils/core/omphalos/render_address.py
coils/core/omphalos/render_appointment.py
coils/core/omphalos/render_blob.py
coils/core/omphalos/render_collection.py
coils/core/omphalos/render_contact.py
coils/core/omphalos/render_enterprise.py
coils/core/omphalos/render_lock.py
coils/core/omphalos/render_object.py
coils/core/omphalos/render_process.py
coils/core/omphalos/render_project.py
coils/core/omphalos/render_route.py
coils/core/omphalos/render_task.py
coils/core/omphalos/render_team.py
coils/core/omphalos/render_timezone.py
coils/core/omphalos/utility.py
