Metadata-Version: 1.1
Name: OpenGroupware
Version: 0.1.48
Summary: OpenGroupware Coils Groupware & Workflow Solution
Home-page: http://sourceforge.net/projects/coils/
Author: Adam Tauno Williams
Author-email: awilliam@opengroupware.us
License: MIT/X11
Keywords: groupware workflow bpml
Platform: UNKNOWN
Classifier: Development Status :: 3 - Alpha
Classifier: Environment :: Web Environment
Classifier: Intended Audience :: Developers
Classifier: Intended Audience :: Information Technology
Classifier: License :: OSI Approved :: MIT License
Classifier: Operating System :: POSIX
Classifier: Programming Language :: Python :: 2.6
Classifier: Topic :: Communications :: Email
Classifier: Topic :: Office/Business :: Scheduling
Classifier: Topic :: Software Development :: Libraries :: Application Frameworks
Classifier: Topic :: Software Development :: Libraries :: Python Modules
Classifier: Topic :: Office/Business :: Groupware
Classifier: Topic :: Other/Nonlisted Topic
